[
    {
        "error_reason": "No explicit Python Tracebacks found in the logs",
        "command_tried": "orchestrator_fix_attempt",
        "error_response": "Judge Score: 0.7, Sandbox Valid: False",
        "timestamp": "2026-04-03T12:54:53.240296"
    },
    {
        "error_reason": "No explicit Python Tracebacks found, but potential issues may exist",
        "command_tried": "orchestrator_fix_attempt",
        "error_response": "Judge Score: 0.0, Sandbox Valid: True",
        "timestamp": "2026-04-03T13:02:17.377937"
    },
    {
        "error_reason": "No explicit Python Tracebacks found, but potential issues in dependency management",
        "command_tried": "orchestrator_fix_attempt",
        "error_response": "Judge Score: 0.0, Sandbox Valid: True",
        "timestamp": "2026-04-03T13:02:17.865859"
    },
    {
        "error_reason": "No explicit Python Tracebacks found in the CI/CD logs",
        "command_tried": "orchestrator_fix_attempt",
        "error_response": "Judge Score: 0.0, Sandbox Valid: True",
        "timestamp": "2026-04-03T13:02:38.030058"
    },
    {
        "error_reason": "ModuleNotFoundError: No module named 'flask'",
        "command_tried": "orchestrator_fix_attempt",
        "error_response": "Judge Score: 0.0, Sandbox Valid: True",
        "timestamp": "2026-04-03T13:03:34.866426"
    },
    {
        "error_reason": "SyntaxError: invalid syntax",
        "command_tried": "orchestrator_fix_attempt",
        "error_response": "Judge Score: 0.0, Sandbox Valid: True",
        "timestamp": "2026-04-03T19:09:17.463886"
    },
    {
        "error_reason": "SyntaxError: invalid syntax",
        "command_tried": "orchestrator_fix_attempt",
        "error_response": "Judge Score: 0.0, Sandbox Valid: True",
        "timestamp": "2026-04-06T17:45:46.417350"
    },
    {
        "error_reason": "SyntaxError: invalid syntax",
        "command_tried": "orchestrator_fix_attempt",
        "error_response": "Judge Score: 0.0, Sandbox Valid: True",
        "timestamp": "2026-04-06T17:45:54.119463"
    },
    {
        "error_reason": "SyntaxError: expected ':'",
        "command_tried": "orchestrator_fix_attempt",
        "error_response": "Judge Score: 0.0, Sandbox Valid: True",
        "timestamp": "2026-04-06T17:50:14.336221"
    },
    {
        "error_reason": "SyntaxError: expected ':'",
        "command_tried": "orchestrator_fix_attempt",
        "error_response": "Judge Score: 0.0, Sandbox Valid: True",
        "timestamp": "2026-04-07T21:09:22.092558"
    }
]